JadeMath/__init__.py
JadeMath/math.py
JadeMath/random.py
JadeMath/surfarea.py
JadeMath/volume.py
JadeMath-2.0.13.dist-info/LICENSE
JadeMath-2.0.13.dist-info/METADATA
JadeMath-2.0.13.dist-info/WHEEL
JadeMath-2.0.13.dist-info/top_level.txt
JadeMath-2.0.13.dist-info/RECORD
