Metadata-Version: 2.1
Name: JadeMath
Version: 2.0.13
Summary: Package Used for solving math
Author: Jade
License: UNKNOWN
Platform: UNKNOWN
Classifier: Programming Language :: Python :: 3
Classifier: License :: OSI Approved :: MIT License
Classifier: Operating System :: OS Independent
Requires-Python: >=3.6
License-File: LICENSE
